cosmos_rl/__init__.py
cosmos_rl/_version.py
cosmos_rl/cli/__init__.py
cosmos_rl/cli/algo.py
cosmos_rl/cli/cli.py
cosmos_rl/cli/custom_group.py
cosmos_rl/cli/nccl.py
cosmos_rl/cli/profiler.py
cosmos_rl/cli/replica.py
cosmos_rl/cli/utils.py
cosmos_rl/colocated/__init__.py
cosmos_rl/colocated/api_client.py
cosmos_rl/colocated/controller.py
cosmos_rl/colocated/rl_worker.py
cosmos_rl/colocated/utils.py
cosmos_rl/comm/__init__.py
cosmos_rl/comm/base.py
cosmos_rl/dispatcher/__init__.py
cosmos_rl/dispatcher/command.py
cosmos_rl/dispatcher/controller.py
cosmos_rl/dispatcher/protocol.py
cosmos_rl/dispatcher/replica.py
cosmos_rl/dispatcher/run_web_panel.py
cosmos_rl/dispatcher/status.py
cosmos_rl/dispatcher/algo/__init__.py
cosmos_rl/dispatcher/algo/base.py
cosmos_rl/dispatcher/algo/grpo.py
cosmos_rl/dispatcher/algo/reward.py
cosmos_rl/dispatcher/api/client.py
cosmos_rl/dispatcher/config/__init__.py
cosmos_rl/dispatcher/config/frontend/__init__.py
cosmos_rl/dispatcher/config/frontend/configure_template.html
cosmos_rl/dispatcher/config/frontend/dispatcher_status.html
cosmos_rl/dispatcher/data/__init__.py
cosmos_rl/dispatcher/data/data_fetcher.py
cosmos_rl/dispatcher/data/schema.py
cosmos_rl/dispatcher/data/packer/__init__.py
cosmos_rl/dispatcher/data/packer/base.py
cosmos_rl/dispatcher/data/packer/decoder_only_llm_data_packer.py
cosmos_rl/dispatcher/data/packer/deepseek_data_packer.py
cosmos_rl/dispatcher/data/packer/hf_vlm_data_packer.py
cosmos_rl/dispatcher/data/packer/multi_turn.py
cosmos_rl/dispatcher/data/packer/pi05_data_packer.py
cosmos_rl/dispatcher/data/packer/qwen2_5_vlm_data_packer.py
cosmos_rl/dispatcher/data/packer/qwen3_vl_data_packer.py
cosmos_rl/dispatcher/data/packer/vla_data_packer.py
cosmos_rl/launcher/__init__.py
cosmos_rl/launcher/launch_all.py
cosmos_rl/launcher/launch_controller.sh
cosmos_rl/launcher/launch_replica.sh
cosmos_rl/launcher/launch_vision.py
cosmos_rl/launcher/utility.py
cosmos_rl/launcher/worker_entry.py
cosmos_rl/patch/__init__.py
cosmos_rl-0.3.9.dist-info/licenses/LICENSE
cosmos_rl-0.3.9.dist-info/METADATA
cosmos_rl-0.3.9.dist-info/WHEEL
cosmos_rl-0.3.9.dist-info/entry_points.txt
cosmos_rl-0.3.9.dist-info/top_level.txt
cosmos_rl-0.3.9.dist-info/RECORD
