Metadata-Version: 2.4
Name: cosmos-rl
Version: 0.3.9
Summary: Cosmos-RL is a flexible and scalable Reinforcement Learning framework specialized for Physical AI applications.
Project-URL: Homepage, https://github.com/nvidia-cosmos/cosmos-rl
Requires-Python: >=3.10
License-File: LICENSE
Requires-Dist: fastapi
Requires-Dist: uvicorn
Requires-Dist: transformers!=4.52.*,!=4.53.*,>=4.51.1
Requires-Dist: datasets>=4.4.1
Requires-Dist: pydantic
Requires-Dist: math_verify
Requires-Dist: nest_asyncio
Requires-Dist: pybind11[global]
Requires-Dist: vllm>=0.8.5
Requires-Dist: torch>=2.6.0
Requires-Dist: torchvision>=0.21.0
Requires-Dist: torchao>=0.10.0
Requires-Dist: tensordict==0.7.2
Requires-Dist: toml
Requires-Dist: StrEnum
Requires-Dist: redis
Requires-Dist: msgpack
Requires-Dist: qwen_vl_utils
Requires-Dist: pynvml
Requires-Dist: boto3
Requires-Dist: modelscope
Requires-Dist: cloudpickle
Requires-Dist: click
Requires-Dist: rich
Requires-Dist: pyyaml
Requires-Dist: blobfile
Requires-Dist: nvidia-nccl-cu12>=2.26.2
Requires-Dist: liger_kernel
Requires-Dist: accelerate
Requires-Dist: kernels
Requires-Dist: diffusers
Requires-Dist: peft
Requires-Dist: flash-attn>=2.8.3
Provides-Extra: wfm
Requires-Dist: termcolor; extra == "wfm"
Requires-Dist: aioboto3; extra == "wfm"
Requires-Dist: aiobotocore; extra == "wfm"
Requires-Dist: imageio; extra == "wfm"
Requires-Dist: imageio-ffmpeg; extra == "wfm"
Requires-Dist: webdataset; extra == "wfm"
Requires-Dist: decord; extra == "wfm"
Requires-Dist: trimesh; extra == "wfm"
Provides-Extra: vla
Requires-Dist: bddl; extra == "vla"
Requires-Dist: easydict; extra == "vla"
Requires-Dist: einops; extra == "vla"
Requires-Dist: future; extra == "vla"
Requires-Dist: gym; extra == "vla"
Requires-Dist: hydra-core; extra == "vla"
Requires-Dist: libero; extra == "vla"
Requires-Dist: math-verify; extra == "vla"
Requires-Dist: matplotlib; extra == "vla"
Requires-Dist: numpy<2; extra == "vla"
Requires-Dist: opencv-python; extra == "vla"
Requires-Dist: robomimic; extra == "vla"
Requires-Dist: robosuite==1.4; extra == "vla"
Requires-Dist: thop; extra == "vla"
Requires-Dist: timm<1; extra == "vla"
Requires-Dist: wandb>0.13.1; extra == "vla"
Provides-Extra: all
Requires-Dist: cosmos_rl[vla,wfm]; extra == "all"
Dynamic: license-file
